LICENSE
MANIFEST.in
README.rst
setup.py
src/django_4store.egg-info/PKG-INFO
src/django_4store.egg-info/SOURCES.txt
src/django_4store.egg-info/dependency_links.txt
src/django_4store.egg-info/requires.txt
src/django_4store.egg-info/top_level.txt
src/fourstore/__init__.py
src/fourstore/fixtures.py
src/fourstore/models.py
src/fourstore/server.py
src/fourstore/test.py
src/fourstore/test_urls.py
src/fourstore/tests.py
src/fourstore/testsettings.py
src/fourstore/urls.py
src/fourstore/utils.py
src/fourstore/views.py
src/fourstore/management/__init__.py
src/fourstore/management/commands/4store-import.py
src/fourstore/management/commands/4store.py
src/fourstore/management/commands/__init__.py