Metadata-Version: 1.0
Name: django-4store
Version: 0.3
Summary: A small Django application that makes developing with the 4Store RDF database easier.
Home-page: http://github.com/66laps/django-fourstore
Author: Martin Galpin
Author-email: m@66laps.com
License: LGPL v3
Platform: UNKNOWN
Classifier: Development Status :: 4 - Beta
Classifier: Framework :: Django
Classifier: Intended Audience :: Developers
Classifier: License :: OSI Approved :: BSD License
Classifier: Operating System :: OS Independent
Classifier: Programming Language :: Python
Classifier: Topic :: Internet :: WWW/HTTP
